scista/__init__.py
scista/article_fetcher.py
scista-0.1.3.dist-info/LICENSE
scista-0.1.3.dist-info/METADATA
scista-0.1.3.dist-info/WHEEL
scista-0.1.3.dist-info/top_level.txt
scista-0.1.3.dist-info/RECORD
